[
  { "id": "tf-501", "domain": "Understand infrastructure as code (IaC) concepts", "question": "Which is the strongest argument for codifying infrastructure?", "choices": ["It is trendy", "Repeatable, reviewable, automatable infrastructure with history", "It removes cloud bills", "It avoids planning"], "correctAnswer": 1, "explanation": "The core IaC value is repeatability, reviewability, automation, and an auditable history of infrastructure changes." },
  { "id": "tf-502", "domain": "Understand infrastructure as code (IaC) concepts", "question": "Which practice reduces snowflake servers?", "choices": ["Manual SSH tweaks", "Provisioning from code and replacing rather than patching", "No version control", "Ad-hoc console edits"], "correctAnswer": 1, "explanation": "Codified provisioning plus immutable replacement avoids unique, hand-tuned snowflake servers." },
  { "id": "tf-503", "domain": "Understand infrastructure as code (IaC) concepts", "question": "How does IaC support compliance audits?", "choices": ["By hiding changes", "Code + VCS history provides a clear, reviewable record of infrastructure", "By disabling logs", "By preventing changes"], "correctAnswer": 1, "explanation": "Version-controlled IaC yields an auditable trail of who changed what and when, aiding compliance." },
  { "id": "tf-504", "domain": "Understand infrastructure as code (IaC) concepts", "question": "Which is true about declarative IaC and ordering?", "choices": ["You must specify exact order", "The tool derives order from dependencies", "Order is random and unsafe", "Order is alphabetical only"], "correctAnswer": 1, "explanation": "Declarative tools infer execution order from resource dependencies rather than requiring explicit step sequencing." },
  { "id": "tf-505", "domain": "Understand the purpose of Terraform (vs other IaC)", "question": "Which complements Terraform for in-OS software setup?", "choices": ["Another provisioning tool only", "Configuration management tools like Ansible/Chef/Puppet", "A spreadsheet", "Nothing is needed"], "correctAnswer": 1, "explanation": "Terraform provisions; configuration management tools handle software installation/config inside the provisioned machines." },
  { "id": "tf-506", "domain": "Understand the purpose of Terraform (vs other IaC)", "question": "Which is accurate about Terraform's idempotent applies?", "choices": ["Every apply recreates resources", "Re-applying unchanged config does nothing", "Apply is never idempotent", "Idempotency needs HCP"], "correctAnswer": 1, "explanation": "Because of state-based diffing, applying unchanged configuration results in no changes — idempotency." },
  { "id": "tf-507", "domain": "Understand the purpose of Terraform (vs other IaC)", "question": "Which is the role of HCL in Terraform?", "choices": ["It stores state", "It is the configuration language describing desired infrastructure", "It is a provider", "It is the backend"], "correctAnswer": 1, "explanation": "HashiCorp Configuration Language (HCL) is the human-friendly language used to declare Terraform configuration." },
  { "id": "tf-508", "domain": "Understand the purpose of Terraform (vs other IaC)", "question": "Why is Terraform suitable for ephemeral environments (e.g., PR previews)?", "choices": ["It cannot destroy", "It can quickly create and fully destroy consistent environments on demand", "It needs manual builds", "It forbids automation"], "correctAnswer": 1, "explanation": "Terraform can stand up and tear down consistent environments programmatically, ideal for ephemeral preview environments." },
  { "id": "tf-509", "domain": "Understand Terraform basics", "question": "Which is true about the terraform block's backend setting?", "choices": ["It defines resources", "It configures where state is stored and how it is accessed", "It sets credentials", "It declares outputs"], "correctAnswer": 1, "explanation": "The backend setting configures state storage/access (local, s3, remote, etc.)." },
  { "id": "tf-510", "domain": "Understand Terraform basics", "question": "Which describes terraform init -reconfigure?", "choices": ["Migrates state automatically", "Reinitializes the backend ignoring existing saved settings (no state migration prompt)", "Applies changes", "Formats files"], "correctAnswer": 1, "explanation": "-reconfigure reinitializes the backend using the current configuration without attempting to migrate existing state." },
  { "id": "tf-511", "domain": "Understand Terraform basics", "question": "Which is a correct provider requirement entry?", "choices": ["google = { source = \"hashicorp/google\", version = \">= 4.0\" }", "google = latest", "google: 4", "provider google 4"], "correctAnswer": 0, "explanation": "Each required_providers entry maps a local name to an object with source and version." },
  { "id": "tf-512", "domain": "Understand Terraform basics", "question": "What is the effect of omitting a backend block?", "choices": ["No state is kept", "Terraform uses the default local backend", "It errors", "It uses HCP automatically"], "correctAnswer": 1, "explanation": "Without a backend block, Terraform defaults to local state storage." },
  { "id": "tf-513", "domain": "Understand Terraform basics", "question": "Which is true about referencing resource attributes?", "choices": ["<type>.<name>.<attribute>", "var.<type>.<name>", "data only", "It is not possible"], "correctAnswer": 0, "explanation": "Managed resource attributes are referenced as <type>.<name>.<attribute>." },
  { "id": "tf-514", "domain": "Understand Terraform basics", "question": "What does the depends_on meta-argument express?", "choices": ["A provider alias", "An explicit dependency Terraform can't infer", "An output", "A backend"], "correctAnswer": 1, "explanation": "depends_on declares explicit ordering when there is no attribute reference for Terraform to infer it." },
  { "id": "tf-515", "domain": "Use the core Terraform workflow", "question": "Which is the correct minimal lifecycle for first-time provisioning?", "choices": ["init → plan → apply", "plan → apply", "apply only", "validate only"], "correctAnswer": 0, "explanation": "init prepares the directory; plan previews; apply executes — the minimal correct sequence." },
  { "id": "tf-516", "domain": "Use the core Terraform workflow", "question": "Which symbol means 'in-place update'?", "choices": ["+", "-", "~", "-/+"], "correctAnswer": 2, "explanation": "~ indicates an in-place modification without replacement." },
  { "id": "tf-517", "domain": "Use the core Terraform workflow", "question": "What does applying a saved plan guarantee versus interactive apply?", "choices": ["Random changes", "Exactly the reviewed actions are applied", "More prompts", "State deletion"], "correctAnswer": 1, "explanation": "A saved plan applies precisely the reviewed set of actions with no re-planning." },
  { "id": "tf-518", "domain": "Use the core Terraform workflow", "question": "Which is the recommended replacement-forcing approach today?", "choices": ["terraform taint", "terraform apply -replace=ADDR", "delete state", "edit tfstate"], "correctAnswer": 1, "explanation": "-replace supersedes the deprecated taint command for forcing recreation." },
  { "id": "tf-519", "domain": "Use the core Terraform workflow", "question": "When is prevent_destroy especially valuable?", "choices": ["For throwaway resources", "For critical resources like production databases", "For modules", "For outputs"], "correctAnswer": 1, "explanation": "prevent_destroy guards critical resources by erroring if a plan would destroy them." },
  { "id": "tf-520", "domain": "Use the core Terraform workflow", "question": "Which describes a speculative/local plan?", "choices": ["It applies changes", "It previews changes without modifying infrastructure", "It deletes state", "It installs providers only"], "correctAnswer": 1, "explanation": "A plan previews proposed changes without applying them, supporting safe review." },
  { "id": "tf-521", "domain": "Use the core Terraform workflow", "question": "Which flag would you add to apply in automation to avoid hanging on prompts?", "choices": ["-input=false (and often -auto-approve)", "-interactive", "-prompt", "-wait"], "correctAnswer": 0, "explanation": "-input=false prevents interactive prompts; -auto-approve skips the confirmation, both common in CI." },
  { "id": "tf-522", "domain": "Use the core Terraform workflow", "question": "What does Terraform do when two independent resources have no dependency?", "choices": ["Runs them sequentially always", "May create them in parallel", "Refuses to plan", "Imports them"], "correctAnswer": 1, "explanation": "Independent graph nodes can be operated on concurrently to speed up runs." },
  { "id": "tf-523", "domain": "Implement and maintain state", "question": "Which is a correct statement about the s3 backend?", "choices": ["It cannot lock", "It stores state in S3 and supports locking (DynamoDB or native S3 locking)", "It needs no bucket", "It encrypts the config"], "correctAnswer": 1, "explanation": "The s3 backend stores state in a bucket and supports locking via DynamoDB or newer native S3 lock mechanisms." },
  { "id": "tf-524", "domain": "Implement and maintain state", "question": "Which command relocates a resource within state?", "choices": ["terraform state mv", "terraform move", "terraform relocate", "terraform shift"], "correctAnswer": 0, "explanation": "terraform state mv changes a resource's address in state without recreating it." },
  { "id": "tf-525", "domain": "Implement and maintain state", "question": "Why must classic terraform import be paired with writing configuration?", "choices": ["Import writes config automatically", "Without config the next plan would propose destroying the imported resource", "Config is irrelevant", "Import deletes the resource"], "correctAnswer": 1, "explanation": "Classic import only records the object in state; matching configuration is required so it isn't seen as removed." },
  { "id": "tf-526", "domain": "Implement and maintain state", "question": "Which protects against two engineers applying simultaneously?", "choices": ["fmt", "State locking via the backend", "Outputs", "The lock file (.terraform.lock.hcl)"], "correctAnswer": 1, "explanation": "Backend state locking serializes operations; the dependency lock file is unrelated (it pins providers)." },
  { "id": "tf-527", "domain": "Implement and maintain state", "question": "What does terraform state rm do to the real resource?", "choices": ["Destroys it", "Leaves it untouched while removing it from state", "Imports it", "Renames it"], "correctAnswer": 1, "explanation": "state rm only unbinds management; the real object continues to exist." },
  { "id": "tf-528", "domain": "Implement and maintain state", "question": "Which is the safest place for production state?", "choices": ["A laptop", "A secured, versioned, locked remote backend", "A public repo", "An email folder"], "correctAnswer": 1, "explanation": "Production state belongs in a secured remote backend with versioning and locking for safety and collaboration." },
  { "id": "tf-529", "domain": "Implement and maintain state", "question": "Which describes the moved block's benefit during module refactors?", "choices": ["It locks state", "It declaratively maps old to new addresses to avoid destroy/recreate", "It deletes resources", "It changes providers"], "correctAnswer": 1, "explanation": "moved blocks record address changes so refactors don't trigger destruction and recreation." },
  { "id": "tf-530", "domain": "Read, generate, and modify configuration", "question": "Which function returns a value from a map with a default if missing?", "choices": ["lookup(map, key, default)", "get(map, key)", "map.key", "fetch(map, key)"], "correctAnswer": 0, "explanation": "lookup(map, key, default) returns the value or the provided default when the key is absent." },
  { "id": "tf-531", "domain": "Read, generate, and modify configuration", "question": "Which is a correct list-comprehension that filters?", "choices": ["[for s in var.l : s if s != \"\"]", "filter(var.l)", "for s in var.l where s", "select(var.l)"], "correctAnswer": 0, "explanation": "A for expression supports an if clause to filter elements: [for s in var.l : s if s != \"\"]." },
  { "id": "tf-532", "domain": "Read, generate, and modify configuration", "question": "Which converts JSON text into a Terraform value?", "choices": ["jsondecode()", "jsonencode()", "fromjson()", "parse()"], "correctAnswer": 0, "explanation": "jsondecode() parses a JSON string into a Terraform value; jsonencode() does the reverse." },
  { "id": "tf-533", "domain": "Read, generate, and modify configuration", "question": "What does the zipmap() function do?", "choices": ["Compresses a map", "Builds a map from a list of keys and a list of values", "Sorts a map", "Locks state"], "correctAnswer": 1, "explanation": "zipmap(keys, values) constructs a map by pairing the keys list with the values list positionally." },
  { "id": "tf-534", "domain": "Read, generate, and modify configuration", "question": "Which is a correct use of the splat operator?", "choices": ["aws_subnet.this[*].id", "aws_subnet.this.*.id only in old HCL — both forms exist; [*] is current", "subnet.id[*]", "splat(aws_subnet.this)"], "correctAnswer": 0, "explanation": "The modern splat aws_subnet.this[*].id collects the id from all instances into a list." },
  { "id": "tf-535", "domain": "Read, generate, and modify configuration", "question": "What does sensitive() function do to a value?", "choices": ["Decrypts it", "Marks the value as sensitive so it is redacted in output", "Validates it", "Imports it"], "correctAnswer": 1, "explanation": "sensitive() marks a value sensitive, causing Terraform to redact it from plan/apply output." },
  { "id": "tf-536", "domain": "Read, generate, and modify configuration", "question": "Which is true about heredoc <<-EOT vs <<EOT?", "choices": ["No difference", "<<-EOT strips leading indentation; <<EOT preserves it", "<<-EOT encrypts", "<<EOT is invalid"], "correctAnswer": 1, "explanation": "The indented heredoc marker <<- removes leading whitespace, useful for nicely indented multi-line strings." },
  { "id": "tf-537", "domain": "Interact with Terraform modules", "question": "Which is the correct way to pass a list into a child module?", "choices": ["Set the module block argument equal to the list value", "Edit the child's state", "Use an output", "It is not allowed"], "correctAnswer": 0, "explanation": "Pass values by setting the child's input variable as an argument in the module block (e.g., subnets = var.subnets)." },
  { "id": "tf-538", "domain": "Interact with Terraform modules", "question": "What is true about local modules and versioning?", "choices": ["They support version constraints", "They do not use version constraints (only registry/remote do)", "They must be versioned", "They cannot have inputs"], "correctAnswer": 1, "explanation": "Local path modules are not versioned; version constraints apply to registry/remote sources." },
  { "id": "tf-539", "domain": "Interact with Terraform modules", "question": "Which addresses a for_each module instance keyed \"prod\"?", "choices": ["module.env[\"prod\"]", "module.prod.env", "env.module[\"prod\"]", "module.env.prod"], "correctAnswer": 0, "explanation": "for_each module instances are addressed module.<name>[<key>], so module.env[\"prod\"]." },
  { "id": "tf-540", "domain": "Interact with Terraform modules", "question": "Why expose only necessary module outputs?", "choices": ["To leak internals", "To keep a clean, stable interface for consumers", "To slow plans", "To disable providers"], "correctAnswer": 1, "explanation": "A minimal, intentional output surface keeps the module's interface clean and stable for consumers." },
  { "id": "tf-541", "domain": "Interact with Terraform modules", "question": "Which is the effect of a child module changing without input changes during apply?", "choices": ["No effect", "Terraform plans the internal resource changes", "It deletes the module", "It re-imports resources"], "correctAnswer": 1, "explanation": "Internal module edits change managed resources; plan/apply reflect them normally." },
  { "id": "tf-542", "domain": "Interact with Terraform modules", "question": "Which is a recommended source for production modules with governance?", "choices": ["Random Git fork", "Versioned registry (public verified or HCP private)", "Pasted snippets", "Email"], "correctAnswer": 1, "explanation": "Versioned registries (verified public or HCP private) provide governed, reliable module sourcing for production." },
  { "id": "tf-543", "domain": "Use Terraform outside the core workflow", "question": "Which command would generate import configuration scaffolding in newer Terraform when used with -generate-config-out?", "choices": ["terraform plan -generate-config-out=generated.tf (with import blocks)", "terraform fmt", "terraform output", "terraform get"], "correctAnswer": 0, "explanation": "With import blocks, terraform plan -generate-config-out=FILE can scaffold resource configuration for imported objects." },
  { "id": "tf-544", "domain": "Use Terraform outside the core workflow", "question": "What does terraform validate NOT do?", "choices": ["Check syntax", "Check internal consistency", "Contact remote provider APIs", "Use initialized providers' schemas"], "correctAnswer": 2, "explanation": "validate uses provider schemas locally but does not contact remote APIs or require valid credentials." },
  { "id": "tf-545", "domain": "Use Terraform outside the core workflow", "question": "Which is appropriate to pretty-print and standardize code before commit?", "choices": ["terraform fmt", "terraform destroy", "terraform apply", "terraform import"], "correctAnswer": 0, "explanation": "terraform fmt standardizes formatting and is a good pre-commit step." },
  { "id": "tf-546", "domain": "Use Terraform outside the core workflow", "question": "Which command yields a single output value without quotes for scripting?", "choices": ["terraform output -raw NAME", "terraform output NAME -pretty", "terraform show NAME", "terraform get NAME"], "correctAnswer": 0, "explanation": "-raw prints the value with no quotes/formatting, convenient for shell variable capture." },
  { "id": "tf-547", "domain": "Use Terraform outside the core workflow", "question": "Which command can display the current state in JSON for tooling?", "choices": ["terraform show -json", "terraform fmt -json", "terraform get -json", "terraform init -json"], "correctAnswer": 0, "explanation": "terraform show -json renders state (or a plan) as structured JSON for automation/policy tools." },
  { "id": "tf-548", "domain": "Understand Terraform Cloud capabilities", "question": "Which is a primary HCP Terraform value proposition?", "choices": ["Local-only operation", "Collaboration: shared state, remote runs, RBAC, policy, registry", "No state", "Imperative scripting"], "correctAnswer": 1, "explanation": "HCP Terraform centralizes collaboration features: shared state, remote runs, access control, policy, and a private registry." },
  { "id": "tf-549", "domain": "Understand Terraform Cloud capabilities", "question": "What does a workspace's manual apply setting enforce?", "choices": ["Automatic applies", "A human must approve the run after reviewing the plan", "No plan", "No state"], "correctAnswer": 1, "explanation": "Manual apply requires explicit approval of the plan before the apply proceeds." },
  { "id": "tf-550", "domain": "Understand Terraform Cloud capabilities", "question": "Which feature lets HCP Terraform enforce 'no public S3 buckets' before apply?", "choices": ["Policy as code (Sentinel/OPA)", "terraform fmt", "Local backend", "The graph"], "correctAnswer": 0, "explanation": "Policy-as-code evaluates the plan and can block applies that violate organizational rules like prohibiting public buckets." }
]
